syre_excel_template_runner/__about__.py
syre_excel_template_runner/__init__.py
syre_excel_template_runner/__main__.py
syre_excel_template_runner/excel_template_runner.py
syre_excel_template_runner/types.py
syre_excel_template_runner/utils.py
syre_excel_template_runner-0.0.2.dist-info/METADATA
syre_excel_template_runner-0.0.2.dist-info/WHEEL
syre_excel_template_runner-0.0.2.dist-info/licenses/LICENSE.txt
syre_excel_template_runner-0.0.2.dist-info/RECORD
