Metadata-Version: 2.1
Name: syre-excel-template-runner
Version: 0.0.2
Summary: Excel template runner for Syre.
Project-URL: Documentation, https://github.com/syre-data/excel-template-runner#readme
Project-URL: Issues, https://github.com/syre-data/excel-template-runner/issues
Project-URL: Source, https://github.com/syre-data/excel-template-runner
Author-email: Brian Carlsen <carlsen.bri@gmail.com>
License-Expression: MIT
License-File: LICENSE.txt
Keywords: syre
Classifier: Development Status :: 4 - Beta
Classifier: Programming Language :: Python
Classifier: Programming Language :: Python :: 3.8
Classifier: Programming Language :: Python :: 3.9
Classifier: Programming Language :: Python :: 3.10
Classifier: Programming Language :: Python :: 3.11
Classifier: Programming Language :: Python :: 3.12
Classifier: Programming Language :: Python :: Implementation :: CPython
Classifier: Programming Language :: Python :: Implementation :: PyPy
Requires-Python: >=3.8
Requires-Dist: openpyxl
Requires-Dist: pandas
Requires-Dist: syre
Requires-Dist: syre-formulas
